TriesWithFrequencies/TriesWithFrequencies.py
TriesWithFrequencies/__init__.py
TriesWithFrequencies-0.0.1.dist-info/LICENSE
TriesWithFrequencies-0.0.1.dist-info/METADATA
TriesWithFrequencies-0.0.1.dist-info/WHEEL
TriesWithFrequencies-0.0.1.dist-info/top_level.txt
TriesWithFrequencies-0.0.1.dist-info/RECORD
