Metadata-Version: 2.1
Name: TriesWithFrequencies
Version: 0.0.1
Summary: This package provides tries (prefix trees) with frequencies implementation based on dictionaries.
Home-page: https://github.com/antononcube/Python-packages/tree/main/TriesWithFrequencies
Author: Anton Antonov
Author-email: antononcube@posteo.net
Keywords: trie,prefix tree,frequency,frequencies
Classifier: Intended Audience :: Science/Research
Classifier: Intended Audience :: Developers
Classifier: Programming Language :: Python :: 3
Classifier: License :: OSI Approved :: BSD License
Classifier: Intended Audience :: Science/Research
Classifier: Intended Audience :: Developers
Classifier: Operating System :: OS Independent
Requires-Python: >=3.7
License-File: LICENSE
